CHANGELOG.rst
LICENSE
MANIFEST.in
README.md
requirements.txt
setup.py
tox.ini
alembic/README
alembic/env.py
alembic/script.py.mako
alembic/versions/140c0dd3605_added_fields_for_local_remote_sockets_.py
alembic/versions/20c114cc162_initial_migration.py
alembic/versions/50135956b24_added_ssl_fields_in_network_table.py
ircb/__init__.py
ircb/bouncer.py
ircb/connection.py
ircb/identd.py
ircb.egg-info/PKG-INFO
ircb.egg-info/SOURCES.txt
ircb.egg-info/dependency_links.txt
ircb.egg-info/entry_points.txt
ircb.egg-info/pbr.json
ircb.egg-info/requires.txt
ircb.egg-info/top_level.txt
ircb/cli/__init__.py
ircb/cli/loaddata.py
ircb/cli/main.py
ircb/cli/network.py
ircb/cli/run.py
ircb/cli/user.py
ircb/config/__init__.py
ircb/config/default_settings.py
ircb/forms/__init__.py
ircb/forms/network.py
ircb/forms/user.py
ircb/irc/__init__.py
ircb/irc/plugins/__init__.py
ircb/irc/plugins/autojoins.py
ircb/irc/plugins/ircb.py
ircb/irc/plugins/logger.py
ircb/lib/async.py
ircb/lib/constants/__init__.py
ircb/lib/constants/signals.py
ircb/lib/dispatcher/__init__.py
ircb/models/__init__.py
ircb/models/channel.py
ircb/models/client.py
ircb/models/lib.py
ircb/models/logs.py
ircb/models/network.py
ircb/models/user.py
ircb/publishers/__init__.py
ircb/publishers/base.py
ircb/publishers/channels.py
ircb/publishers/logs.py
ircb/publishers/networks.py
ircb/storeclient/__init__.py
ircb/storeclient/base.py
ircb/storeclient/channel.py
ircb/storeclient/client.py
ircb/storeclient/logs.py
ircb/storeclient/network.py
ircb/storeclient/user.py
ircb/stores/__init__.py
ircb/stores/base.py
ircb/stores/channel.py
ircb/stores/client.py
ircb/stores/logs.py
ircb/stores/network.py
ircb/stores/user.py
ircb/utils/__init__.py
ircb/utils/config.py
ircb/web/__init__.py
ircb/web/app.py
ircb/web/decorators.py
ircb/web/lib.py
ircb/web/network.py
ircb/web/user.py