Metadata-Version: 1.1
Name: ircb
Version: 0.3.0
Summary: A IRC bouncer
Home-page: UNKNOWN
Author: Ratnadeep Debnath
Author-email: rtnpro@gmail.com
License: MIT
Keywords: irc,client,bouncer
Platform: UNKNOWN
Classifier: Development Status :: 3 - Alpha
Classifier: Intended Audience :: Developers
Classifier: License :: OSI Approved :: MIT License
Classifier: Operating System :: POSIX :: Linux
Classifier: Programming Language :: Python :: 3.5
Classifier: Topic :: Internet :: WWW/HTTP :: WSGI :: Application
